{
    "data": [
        {
            "id": "1",
            "title": "соединительный выступ",
            "descr": "(1-1/RF/B1/B2)",
            "short": "А",
            "basis": true
        },
        {
            "id": "2",
            "title": "выступ-впадина",
            "descr": "(2-3/LMF/E-F)",
            "short": "Б",
            "basis": true
        },
        {
            "id": "3",
            "title": "шип-паз",
            "descr": "(4-5/LTG/C-D)",
            "short": "В",
            "basis": true
        },
        {
            "id": "4",
            "title": "Паз-гладкая поверхность"
        }
    ]
}
